ament_lint_pep257-0.14.3.data/data/share/ament_index/resource_index/packages/ament_pep257
ament_lint_pep257-0.14.3.data/data/share/ament_pep257/package.xml
ament_pep257/__init__.py
ament_pep257/main.py
ament_pep257/pytest_marker.py
ament_lint_pep257-0.14.3.dist-info/METADATA
ament_lint_pep257-0.14.3.dist-info/WHEEL
ament_lint_pep257-0.14.3.dist-info/entry_points.txt
ament_lint_pep257-0.14.3.dist-info/top_level.txt
ament_lint_pep257-0.14.3.dist-info/zip-safe
ament_lint_pep257-0.14.3.dist-info/RECORD
